tests/__init__.py
tests/base.py
tests/test_version.py
xy_cli/__init__.py
xy_cli/__main__.py
xy_cli/version.py
xy_cli/commands/__init__.py
xy_cli/commands/clone.py
xy_cli/commands/faker.py
xy_cli/commands/line.py
xy_cli/commands/say.py
xy_cli/commands/slack.py
xy_cli/commands/version.py
xy_cli/commands/xlsx.py
xy_cli/commands/xml2json.py
xy_cli/libs/DataFactory.py
xy_cli/libs/FileUtil.py
xy_cli/libs/LineNotify.py
xy_cli/libs/XlsxLoader.py
xy_cli/libs/__init__.py
xy_cli/libs/slack.py
xy_cli/libs/tts.py
xy_cli/libs/util.py
xy_cli/libs/xml2json.py
xy_cli-0.8.dist-info/LICENSE
xy_cli-0.8.dist-info/METADATA
xy_cli-0.8.dist-info/WHEEL
xy_cli-0.8.dist-info/entry_points.txt
xy_cli-0.8.dist-info/top_level.txt
xy_cli-0.8.dist-info/RECORD
