Metadata-Version: 2.1
Name: xy-cli
Version: 0.8
Summary: xy command tools
Home-page: https://github.com/exiahuang/xy-cli
Author: exiahuang
Author-email: exia.huang@outlook.com
License: Apache License 2.0
Keywords: xy-cli command line
Platform: UNKNOWN
Classifier: Development Status :: 4 - Beta
Classifier: Intended Audience :: Developers
Classifier: License :: OSI Approved :: Apache Software License
Classifier: Natural Language :: English
Classifier: Operating System :: Unix
Classifier: Programming Language :: Python :: 3.2
Classifier: Programming Language :: Python :: 3.3
Classifier: Programming Language :: Python :: 3.4
Classifier: Programming Language :: Python :: 3.5
Classifier: Programming Language :: Python :: 3.6
Classifier: Programming Language :: Python :: 3.8
Classifier: Programming Language :: Python :: 3.8
Classifier: Programming Language :: Python :: Implementation :: PyPy
Classifier: Operating System :: OS Independent
Requires-Dist: xlrd
Requires-Dist: Faker
Requires-Dist: gTTS
Requires-Dist: xmltodict
Provides-Extra: tests
Requires-Dist: mock ; extra == 'tests'
Requires-Dist: nose ; extra == 'tests'
Requires-Dist: coverage ; extra == 'tests'
Requires-Dist: yanc ; extra == 'tests'
Requires-Dist: preggy ; extra == 'tests'
Requires-Dist: tox ; extra == 'tests'
Requires-Dist: ipdb ; extra == 'tests'
Requires-Dist: coveralls ; extra == 'tests'
Requires-Dist: sphinx ; extra == 'tests'
